Latest_EarthQuake_BMKG/__init__.py
LatestEarthQuakeIndonesiaByFaqih-0.3.dist-info/LICENSE
LatestEarthQuakeIndonesiaByFaqih-0.3.dist-info/METADATA
LatestEarthQuakeIndonesiaByFaqih-0.3.dist-info/WHEEL
LatestEarthQuakeIndonesiaByFaqih-0.3.dist-info/top_level.txt
LatestEarthQuakeIndonesiaByFaqih-0.3.dist-info/RECORD
