Metadata-Version: 2.1
Name: LatestEarthQuakeIndonesiaByFaqih
Version: 0.3
Summary: This package will get latest earthquake from BMKG | Meteorological, Climatological, and Geophysical Agency
Home-page: https://github.com/Fakhr07/Latest-EarthQuake-BMKG
Author: Faqih Fakhruddin
Author-email: faqih0776@gmail.com
License: UNKNOWN
Project-URL: Bug Tracker, https://github.com/Faqih0776
Platform: UNKNOWN
Classifier: Programming Language :: Python :: 3
Classifier: License :: OSI Approved :: GNU General Public License v3 (GPLv3)
Classifier: Operating System :: OS Independent
Classifier: Development Status :: 5 - Production/Stable
Requires-Python: >=3.6
License-File: LICENSE
